mbctools.py
mbctools_test-0.0.5.dist-info/LICENSE
mbctools_test-0.0.5.dist-info/METADATA
mbctools_test-0.0.5.dist-info/WHEEL
mbctools_test-0.0.5.dist-info/entry_points.txt
mbctools_test-0.0.5.dist-info/top_level.txt
mbctools_test-0.0.5.dist-info/RECORD
