Metadata-Version: 2.1
Name: mbctools_test
Version: 0.0.5
Summary: mbctools: A User-Friendly Metabarcoding and Cross-Platform Pipeline for Analyzing Multiple Amplicon Sequencing Data across a Large Diversity of Organisms
Home-page: https://github.com/GuilhemSempere/mbctools/blob/dev/mbctools.py
Author: Christian Barnabe, Guilhem Sempere
Author-email: guilhem.sempere@cirad.fr
License: MIT
Classifier: Programming Language :: Python :: 3
Classifier: License :: OSI Approved :: MIT License
Classifier: Operating System :: OS Independent
Requires-Python: >=3.7
License-File: LICENSE
